Metadata-Version: 2.1
Name: odoo8-addon-base-module-doc-rst
Version: 8.0.1.0.0.99.dev38
Summary: Modules Technical Guides in RST and Relationship Graphs
Home-page: https://odoo-community.org/
Author: OpenERP SA,Odoo Community Association (OCA)
Author-email: support@odoo-community.org
License: AGPL-3
Platform: UNKNOWN
Classifier: Programming Language :: Python
Classifier: Framework :: Odoo
Classifier: Framework :: Odoo :: 8.0
Classifier: License :: OSI Approved :: GNU Affero General Public License v3
Requires-Python: ~=2.7
Requires-Dist: odoo (<9.0a,>=8.0a)
Requires-Dist: pydot
